odoo10_addon_pos_payment_terminal-10.0.1.0.1-py3.8-nspkg.pth
odoo/addons/pos_payment_terminal/README.rst
odoo/addons/pos_payment_terminal/__init__.py
odoo/addons/pos_payment_terminal/__manifest__.py
odoo/addons/pos_payment_terminal/demo/pos_payment_terminal_demo.xml
odoo/addons/pos_payment_terminal/i18n/es.po
odoo/addons/pos_payment_terminal/i18n/fr.po
odoo/addons/pos_payment_terminal/i18n/hr_HR.po
odoo/addons/pos_payment_terminal/i18n/it.po
odoo/addons/pos_payment_terminal/i18n/nl_NL.po
odoo/addons/pos_payment_terminal/i18n/pos_payment_terminal.pot
odoo/addons/pos_payment_terminal/models/__init__.py
odoo/addons/pos_payment_terminal/models/account_journal.py
odoo/addons/pos_payment_terminal/models/pos_config.py
odoo/addons/pos_payment_terminal/models/pos_order.py
odoo/addons/pos_payment_terminal/static/description/icon.png
odoo/addons/pos_payment_terminal/static/src/css/pos_payment_terminal.css
odoo/addons/pos_payment_terminal/static/src/js/pos_payment_terminal.js
odoo/addons/pos_payment_terminal/static/src/xml/pos_payment_terminal.xml
odoo/addons/pos_payment_terminal/tests/__init__.py
odoo/addons/pos_payment_terminal/tests/test_transactions.py
odoo/addons/pos_payment_terminal/views/account_journal.xml
odoo/addons/pos_payment_terminal/views/pos_config.xml
odoo/addons/pos_payment_terminal/views/pos_payment_terminal_template.xml
odoo10_addon_pos_payment_terminal-10.0.1.0.1.dist-info/METADATA
odoo10_addon_pos_payment_terminal-10.0.1.0.1.dist-info/WHEEL
odoo10_addon_pos_payment_terminal-10.0.1.0.1.dist-info/namespace_packages.txt
odoo10_addon_pos_payment_terminal-10.0.1.0.1.dist-info/top_level.txt
odoo10_addon_pos_payment_terminal-10.0.1.0.1.dist-info/RECORD
